trappyscopes/__init__.py
trappyscopes-0.1.1.dist-info/METADATA
trappyscopes-0.1.1.dist-info/WHEEL
trappyscopes-0.1.1.dist-info/RECORD
