Metadata-Version: 2.3
Name: trappyscopes
Version: 0.1.1
Summary: Control Layer Interface for parallel microscopy system.
Author: Yatharth Bhasin
Author-email: yatharth1997@gmail.com
Requires-Python: >=3.12,<4.0
Classifier: Programming Language :: Python :: 3
Classifier: Programming Language :: Python :: 3.12
Classifier: Programming Language :: Python :: 3.13
Requires-Dist: asciichartpy (>=1.5.25,<2.0.0)
Requires-Dist: beepy (>=1.0.9,<2.0.0)
Requires-Dist: colorama (>=0.4.6,<0.5.0)
Requires-Dist: confuse (>=2.0.1,<3.0.0)
Requires-Dist: diagrams (>=0.24.4,<0.25.0)
Requires-Dist: dill (>=0.4.0,<0.5.0)
Requires-Dist: gitpython (>=3.1.45,<4.0.0)
Requires-Dist: graphviz (<=0.21.0)
Requires-Dist: html2rml (>=0.3.2,<0.4.0)
Requires-Dist: imageio-ffmpeg (>=0.6.0,<0.7.0)
Requires-Dist: ipython (>=9.4.0,<10.0.0)
Requires-Dist: ipywidgets (>=8.1.7,<9.0.0)
Requires-Dist: joblib (>=1.5.1,<2.0.0)
Requires-Dist: json-tricks (>=3.17.3,<4.0.0)
Requires-Dist: jupyterlab-widgets (>=3.0.15,<4.0.0)
Requires-Dist: markdown (>=3.8.2,<4.0.0)
Requires-Dist: matplotlib
Requires-Dist: mermaid-py (>=0.8.0,<0.9.0)
Requires-Dist: mpremote (>=1.26.0,<2.0.0)
Requires-Dist: nanoid (>=2.0.0,<3.0.0)
Requires-Dist: numpy (<=2.0.0)
Requires-Dist: openpyxl (>=3.1.5,<4.0.0)
Requires-Dist: paginate (>=0.5.7,<0.6.0)
Requires-Dist: pandas (>=2.3.1,<3.0.0)
Requires-Dist: pathspec (>=0.12.1,<0.13.0)
Requires-Dist: pillow (>=11.3.0,<12.0.0)
Requires-Dist: plotext (>=5.3.2,<6.0.0)
Requires-Dist: prompt-toolkit (>=3.0.51,<4.0.0)
Requires-Dist: pymdown-extensions (>=10.16.1,<11.0.0)
Requires-Dist: pypandoc (>=1.15,<2.0)
Requires-Dist: pyqt5 (>=5.15.11,<6.0.0)
Requires-Dist: pyqt5-qt5 (>=5.15.17,<6.0.0)
Requires-Dist: pyqt5-sip (>=12.17.0,<13.0.0)
Requires-Dist: pyqtgraph (>=0.13.7,<0.14.0)
Requires-Dist: pyserial (>=3.5,<4.0)
Requires-Dist: pyyaml (==6.0.1)
Requires-Dist: qtconsole (>=5.6.1,<6.0.0)
Requires-Dist: qtpy (>=2.4.3,<3.0.0)
Requires-Dist: reportlab (>=4.4.3,<5.0.0)
Requires-Dist: requests (>=2.32.4,<3.0.0)
Requires-Dist: rich (>=14.1.0,<15.0.0)
Requires-Dist: rpyc (>=6.0.2,<7.0.0)
Requires-Dist: schedule (>=1.2.2,<2.0.0)
Requires-Dist: scikit-image (>=0.25.2,<0.26.0)
Requires-Dist: scikit-learn (>=1.7.1,<2.0.0)
Requires-Dist: scipy (>=1.16.1,<2.0.0)
Requires-Dist: smmap (==5.0.1)
Requires-Dist: textual (>=5.3.0,<6.0.0)
Requires-Dist: textual-dev (>=1.7.0,<2.0.0)
Requires-Dist: watchdog (>=6.0.0,<7.0.0)
